sourceRank/SourceRank.py
sourceRank/__init__.py
sourceRank/analysis/__init__.py
sourceRank/analysis/source_credibility_analysis.py
sourceRank/analysis/__pycache__/__init__.cpython-36.pyc
sourceRank/analysis/__pycache__/source_credibility_analysis.cpython-36.pyc
sourceRank/connectors/__init__.py
sourceRank/connectors/news_api_connector.py
sourceRank/connectors/twitter_api_connector.py
sourceRank/connectors/__pycache__/__init__.cpython-36.pyc
sourceRank/connectors/__pycache__/news_api_connector.cpython-36.pyc
sourceRank/connectors/__pycache__/twitter_api_connector.cpython-36.pyc
sourceRank/helper/__init__.py
sourceRank/helper/country_domain_list.py
sourceRank/helper/settings.py
sourceRank/helper/utils.py
sourceRank/helper/__pycache__/__init__.cpython-36.pyc
sourceRank/helper/__pycache__/country_domain_list.cpython-36.pyc
sourceRank/helper/__pycache__/settings.cpython-36.pyc
sourceRank/helper/__pycache__/utils.cpython-36.pyc
sourceRank/models/__init__.py
sourceRank/models/source_credibility_models.py
sourceRank/models/twitter_models.py
sourceRank/models/__pycache__/__init__.cpython-36.pyc
sourceRank/models/__pycache__/source_credibility_models.cpython-36.pyc
sourceRank/models/__pycache__/twitter_models.cpython-36.pyc
sourceRank/resources/resources_domain.csv
sourceRank/resources/resources_domains.csv
sourceRank/unitest/modify_domains.py
sourceRank-2.0.4.dist-info/METADATA
sourceRank-2.0.4.dist-info/WHEEL
sourceRank-2.0.4.dist-info/top_level.txt
sourceRank-2.0.4.dist-info/RECORD
