Metadata-Version: 2.1
Name: sourceRank
Version: 2.0.4
Summary: UNKNOWN
Home-page: UNKNOWN
Author: David Martin-Gutierrez
Author-email: dmargutierrez@gmail.com
License: MIT
Platform: UNKNOWN
Classifier: License :: OSI Approved :: MIT License
Classifier: Programming Language :: Python :: 3
Classifier: Programming Language :: Python :: 3.6
Requires-Python: >=3.6
Requires-Dist: requests
Requires-Dist: tldextract (==3.1.0)
Requires-Dist: tweepy
Requires-Dist: newsapi-python
Requires-Dist: numpy
Requires-Dist: GetOldTweets3
Requires-Dist: coloredlogs
Requires-Dist: fuzzywuzzy
Requires-Dist: scipy
Requires-Dist: pycountry
Requires-Dist: python-dateutil
Requires-Dist: pandas
Requires-Dist: aiodns
Requires-Dist: aiohttp-socks
Requires-Dist: aiohttp
Requires-Dist: cchardet
Requires-Dist: elasticsearch
Requires-Dist: fake-useragent
Requires-Dist: geopy
Requires-Dist: googletransx
Requires-Dist: schedule
Requires-Dist: googlesearch-python
Requires-Dist: python-restcountries
Requires-Dist: twine
Requires-Dist: bumpversion
Requires-Dist: botometer
Requires-Dist: dataclasses
Requires-Dist: langdetect
Requires-Dist: more-itertools
Requires-Dist: python-Levenshtein
Requires-Dist: twint
